CAD_to_OpenMC/__init__.py
CAD_to_OpenMC/assembly.py
CAD_to_OpenMC/assemblymesher.py
CAD_to_OpenMC/assemblymesher_base.py
CAD_to_OpenMC/assemblymesher_cq.py
CAD_to_OpenMC/assemblymesher_cq2.py
CAD_to_OpenMC/assemblymesher_db.py
CAD_to_OpenMC/assemblymesher_gmsh.py
CAD_to_OpenMC/check_step.py
CAD_to_OpenMC/cq_serialize.py
CAD_to_OpenMC/datadirectory.py
CAD_to_OpenMC/meshutils.py
CAD_to_OpenMC/object_factory.py
CAD_to_OpenMC/stl_utils.py
CAD_to_OpenMC-1.0.1.dist-info/LICENSE
CAD_to_OpenMC-1.0.1.dist-info/METADATA
CAD_to_OpenMC-1.0.1.dist-info/WHEEL
CAD_to_OpenMC-1.0.1.dist-info/top_level.txt
CAD_to_OpenMC-1.0.1.dist-info/RECORD
