Metadata-Version: 2.2
Name: CAD_to_OpenMC
Version: 1.0.1
Summary: Package to automagically convert step-geometries to h5m descriptions for neutronics by OpenMC
Author-email: Erik B Knudsen <erik.knudsen@copenhagenatomics.com>
Project-URL: Homepage, https://github.com/openmsr/CAD_to_OpenMC
Project-URL: Bug Tracker, https://github.com/openmsr/CAD_to_OpenMC/issues
Classifier: Programming Language :: Python :: 3
Classifier: License :: OSI Approved :: MIT License
Classifier: Operating System :: OS Independent
Classifier: Development Status :: 4 - Beta
Classifier: Environment :: Console
Requires-Python: >=3.9
License-File: LICENSE
Requires-Dist: gmsh
Requires-Dist: numpy
Requires-Dist: pyparsing
Requires-Dist: cadquery>=2
Requires-Dist: cadquery-ocp>=7
Requires-Dist: numpy
Requires-Dist: networkx
Requires-Dist: unidecode
